plone.synchronize-1.0.3-py2.7-nspkg.pth
plone/synchronize/__init__.py
plone/synchronize/decorator.py
plone/synchronize/tests.py
plone.synchronize-1.0.3.dist-info/DESCRIPTION.rst
plone.synchronize-1.0.3.dist-info/METADATA
plone.synchronize-1.0.3.dist-info/RECORD
plone.synchronize-1.0.3.dist-info/WHEEL
plone.synchronize-1.0.3.dist-info/entry_points.txt
plone.synchronize-1.0.3.dist-info/metadata.json
plone.synchronize-1.0.3.dist-info/namespace_packages.txt
plone.synchronize-1.0.3.dist-info/top_level.txt
