Metadata-Version: 2.0
Name: plone.synchronize
Version: 1.0.3
Summary: Simple decorators to support synchronized methods
Home-page: https://pypi.python.org/pypi/plone.synchronize
Author: Martin Aspeli
Author-email: optilude@gmail.com
License: BSD
Keywords: synchronized lock decorator
Platform: UNKNOWN
Classifier: Programming Language :: Python
Classifier: Programming Language :: Python :: 2.6
Classifier: Programming Language :: Python :: 2.7
Classifier: Programming Language :: Python :: 3.5
Classifier: Topic :: Software Development :: Libraries :: Python Modules
Classifier: License :: OSI Approved :: BSD License
Requires-Dist: setuptools
